Workbook

Sheet Checklist Inventario
A1: INVENTARIO. GPS GASTRONOMKICO
A2: Lista de Verificación — Módulo de Inventario de Mercadería
A4: Restaurante: | C4: Fecha:
A5: Evaluador: | C5: Turno / Servicio:
A7: RESULTADO DE LA EVALUACIÓN
A8: Total de respuestas SÍ | B8: =COUNTIF(B16:B167,"X") -> 1 | C8: Total de respuestas NO | D8: =COUNTIF(C16:C167,"X") -> 1
A9: Ítems evaluados (SÍ + NO) | B9: =B8+D8 -> 2 | C9: % de cumplimiento | D9: =IFERROR(B8/B9,0) -> 0.5
A10: CALIFICACIÓN FINAL | C10: =IF(B9=0,"Sin datos",IF(D9>=0.9,"EXCELENTE",IF(D9>=0.75,"MUY BUENO",IF(D9>=0.6,"ACEPTABLE",IF(D9>=0.4,"RIESGO DE PÉRDIDA DE RENTABILIDAD","SERVICIO CRÍTICO – INTERVENCIÓN INMEDIATA"))))) -> RIESGO DE PÉRDIDA DE RENTABILIDAD
A12: Instrucciones: marque una X en la columna SÍ o NO de cada ítem. Deje en blanco los no aplicables (no se contabilizan). Los totales y la calificación se calculan automáticamente.
A14: 1. RECEPCIÓN DE MERCADERÍA
A15: PREGUNTA | B15: SÍ | C15: NO | D15: OBSERVACIONES
A16: ¿Existe un responsable designado y capacitado para la recepción de mercadería? | B16: X
A17: ¿Se verifica la mercadería contra la orden de compra y el remito (ítems, cantidad y precio)? | C17: X
A18: ¿Se controla el peso de los productos recibidos (no se acepta “a ojo”)?
A19: ¿Se inspeccionan la calidad, la frescura y el estado del empaque al recibir?
A20: ¿Se mide y registra la temperatura de los productos refrigerados y congelados al recibir?
A21: ¿Existe un criterio claro para rechazar mercadería que no cumple los estándares?
A22: ¿Se respeta un horario de recepción definido (fuera de las horas pico)?
A23: ¿La mercadería se ingresa al depósito de inmediato, sin quedar expuesta?
A24: ¿Se documenta cada recepción (fecha, hora, responsable y firma)?
A26: 2. ALMACENAJE DE MERCADERÍA
A27: PREGUNTA | B27: SÍ | C27: NO | D27: OBSERVACIONES
A28: ¿Cada producto tiene una ubicación fija y definida en el depósito?
A29: ¿Los productos se almacenan separados del piso (sobre tarimas o estantes)?
A30: ¿Se respeta la distancia respecto a las paredes para permitir la ventilación?
A31: ¿Las estanterías son de material lavable y se encuentran en buen estado?
A32: ¿El depósito seco se mantiene fresco, seco y ventilado?
A33: ¿Se evita el sobre-stock que dificulta la rotación y ocupa espacio innecesario?
A34: ¿Los productos pesados se ubican en los niveles bajos y los livianos en los altos?
A36: 3. CADENA DE FRÍO Y CONTROL DE TEMPERATURAS
A37: PREGUNTA | B37: SÍ | C37: NO | D37: OBSERVACIONES
A38: ¿Las cámaras, heladeras y freezers tienen termómetro visible y funcional?
A39: ¿Se registran las temperaturas de cada equipo de frío al menos dos veces por día?
A40: ¿Las temperaturas se mantienen en rangos seguros (refrigeración ≤ 5 °C, congelación ≤ -18 °C)?
A41: ¿Existe un plan de acción ante fallas de los equipos o cortes de energía?
A42: ¿Se evita sobrecargar los equipos de frío para permitir la circulación de aire?
A43: ¿Los alimentos calientes se enfrían correctamente antes de refrigerarse?
A45: 4. SISTEMA FIFO / PEPS (rotación)
A46: PREGUNTA | B46: SÍ | C46: NO | D46: OBSERVACIONES
A47: ¿Se aplica el sistema PEPS/FIFO (lo primero que entra es lo primero que sale)?
A48: Se aplica la regla FIFO ( FIRST IN/FIRST OUT)?
A49: ¿La mercadería nueva se ubica detrás de la existente?
A50: ¿El personal está capacitado en el uso del FIFO?
A51: ¿Se controla que no queden productos “olvidados” al fondo o en los rincones?
A52: ¿La rotación se verifica de forma periódica por un responsable?
A54: 5. ROTULACIÓN E IDENTIFICACIÓN
A55: PREGUNTA | B55: SÍ | C55: NO | D55: OBSERVACIONES
A56: ¿Todos los productos fraccionados o trasvasados están rotulados?
A57: ¿El rótulo indica la fecha de recepción o de elaboración?
A58: ¿El rótulo indica la fecha de vencimiento o de consumo preferente?
A59: ¿Se registra la fecha de apertura en los productos una vez abiertos?
A60: ¿Los rótulos son legibles, resistentes a la humedad y están bien adheridos?
A61: ¿Se identifican los alérgenos en los productos cuando corresponde?
A63: 6. UBICACIÓN DE PRODUCTOS SEGÚN CATEGORÍA
A64: PREGUNTA | B64: SÍ | C64: NO | D64: OBSERVACIONES
A65: ¿Los productos están agrupados por categoría (secos, lácteos, cárnicos, limpieza, etc.)?
A66: ¿Los alimentos crudos se almacenan separados y por debajo de los cocidos o listos para consumo?
A67: ¿Los productos de limpieza y los químicos se almacenan separados de los alimentos?
A68: ¿La disposición de los productos evita la contaminación cruzada?
A69: ¿Los alérgenos se almacenan identificados y separados del resto?
A70: ¿La zonificación del depósito está señalizada para facilitar la ubicación?
A72: 7. CONTROL DE STOCK Y REGISTROS
A73: PREGUNTA | B73: SÍ | C73: NO | D73: OBSERVACIONES
A74: ¿Existe un sistema (software, POS o planilla) para registrar entradas y salidas?
A75: ¿Se definieron niveles de stock mínimo, máximo y punto de pedido por producto?
A76: ¿Las salidas de mercadería hacia cocina y barra se registran?
A77: ¿El stock del sistema coincide con el stock físico (sin desvíos significativos)?
A78: ¿Se identifican los productos de mayor valor o criticidad para un control reforzado?
A79: ¿Las compras se planifican según el consumo histórico y no por impulso?
A81: 8. CONTEO E INVENTARIO FÍSICO
A82: PREGUNTA | B82: SÍ | C82: NO | D82: OBSERVACIONES
A83: ¿Se realiza un conteo físico con una frecuencia definida (diario, semanal o mensual según el ítem)?
A84: ¿El conteo lo realiza, cuando es posible, una persona distinta de quien compra?
A85: ¿Se utiliza una planilla o sistema estandarizado para el conteo?
A86: ¿Se concilian las diferencias entre el inventario físico y el del sistema?
A87: ¿Se investigan y documentan las diferencias relevantes?
A88: ¿El inventario se valoriza para conocer el capital inmovilizado?
A90: 9. ACCIONES Y CONTROL ANTE DESVÍOS DEL INVENTARIO
A91: PREGUNTA | B91: SÍ | C91: NO | D91: OBSERVACIONES
A92: ¿Se investigan de forma inmediata las diferencias detectadas entre el stock físico y el del sistema?
A93: ¿Se identifica al responsable del área o del turno donde se originó la falla?
A94: ¿Se advierte al responsable y se da seguimiento al cumplimiento del proceso?
A95: ¿Existe un plan de acción correctivo definido ante un desvío relevante?
A96: ¿Las acciones correctivas se documentan y se verifica su cumplimiento posterior?
A97: ¿Existe un calendario organizado de conteo físico para cada categoría de mercadería?
A98: ¿Se realizan inventarios parciales o especiales, en tiempo y forma, ante fallas en categorías críticas (proteínas, alcohol)?
A99: ¿El dueño o encargado conoce los niveles de stock mínimo y máximo de cada categoría?
A100: ¿Se definen umbrales de desvío aceptables y se actúa cuando se superan?
A101: ¿Las fallas recurrentes derivan en ajustes de proceso o capacitación del personal?
A103: 10. MERMAS, VENCIMIENTOS Y DESPERDICIO
A104: PREGUNTA | B104: SÍ | C104: NO | D104: OBSERVACIONES
A105: ¿Se controlan periódicamente los productos próximos a vencer?
A106: ¿Existe un registro de mermas, roturas y desperdicios?
A107: ¿Se analizan las causas de las mermas para reducirlas?
A108: ¿Se retiran de inmediato los productos vencidos o en mal estado?
A109: ¿Las mermas se consideran en el costo de mercadería vendida (CMV)?
A110: ¿Se aprovechan los recortes y sobrantes de forma planificada, sin afectar la calidad?
A112: 11. HIGIENE Y CONTROL DE PLAGAS DEL DEPÓSITO
A113: PREGUNTA | B113: SÍ | C113: NO | D113: OBSERVACIONES
A114: ¿El depósito y las cámaras se limpian según un cronograma definido?
...

Sheet Bandas y Resumen
A1: BANDAS DE CALIFICACIÓN
A2: % de cumplimiento | B2: Calificación | D2: Acción
A3: Mayor o igual a 90% | B3: Excelente | D3: Sostener y documentar
A4: 75% – 89% | B4: Muy bueno | D4: Ajustar pendientes
A5: 60% – 74% | B5: Aceptable | D5: Plan de mejora
A6: 40% – 59% | B6: Riesgo de pérdida de rentabilidad | D6: Intervención prioritaria
A7: Menor a 40% | B7: Servicio crítico – intervención inmediata | D7: Acción urgente
A9: RESUMEN POR CATEGORÍA
A10: Categoría | B10: SÍ | C10: NO | D10: % Cumpl.
A11: 1. RECEPCIÓN DE MERCADERÍA | B11: =COUNTIF('Checklist Inventario'!B16:B24,"X") -> 1 | C11: =COUNTIF('Checklist Inventario'!C16:C24,"X") -> 1 | D11: =IFERROR(B11/(B11+C11),"-") -> 0.5
A12: 2. ALMACENAJE DE MERCADERÍA | B12: =COUNTIF('Checklist Inventario'!B28:B34,"X") -> 0 | C12: =COUNTIF('Checklist Inventario'!C28:C34,"X") -> 0 | D12: =IFERROR(B12/(B12+C12),"-") -> -
A13: 3. CADENA DE FRÍO Y CONTROL DE TEMPERATURAS | B13: =COUNTIF('Checklist Inventario'!B38:B43,"X") -> 0 | C13: =COUNTIF('Checklist Inventario'!C38:C43,"X") -> 0 | D13: =IFERROR(B13/(B13+C13),"-") -> -
A14: 4. SISTEMA FIFO / PEPS (rotación) | B14: =COUNTIF('Checklist Inventario'!B47:B52,"X") -> 0 | C14: =COUNTIF('Checklist Inventario'!C47:C52,"X") -> 0 | D14: =IFERROR(B14/(B14+C14),"-") -> -
A15: 5. ROTULACIÓN E IDENTIFICACIÓN | B15: =COUNTIF('Checklist Inventario'!B56:B61,"X") -> 0 | C15: =COUNTIF('Checklist Inventario'!C56:C61,"X") -> 0 | D15: =IFERROR(B15/(B15+C15),"-") -> -
A16: 6. UBICACIÓN DE PRODUCTOS SEGÚN CATEGORÍA | B16: =COUNTIF('Checklist Inventario'!B65:B70,"X") -> 0 | C16: =COUNTIF('Checklist Inventario'!C65:C70,"X") -> 0 | D16: =IFERROR(B16/(B16+C16),"-") -> -
A17: 7. CONTROL DE STOCK Y REGISTROS | B17: =COUNTIF('Checklist Inventario'!B74:B79,"X") -> 0 | C17: =COUNTIF('Checklist Inventario'!C74:C79,"X") -> 0 | D17: =IFERROR(B17/(B17+C17),"-") -> -
A18: 8. CONTEO E INVENTARIO FÍSICO | B18: =COUNTIF('Checklist Inventario'!B83:B88,"X") -> 0 | C18: =COUNTIF('Checklist Inventario'!C83:C88,"X") -> 0 | D18: =IFERROR(B18/(B18+C18),"-") -> -
A19: 9. ACCIONES Y CONTROL ANTE DESVÍOS DEL INVENTARIO | B19: =COUNTIF('Checklist Inventario'!B92:B101,"X") -> 0 | C19: =COUNTIF('Checklist Inventario'!C92:C101,"X") -> 0 | D19: =IFERROR(B19/(B19+C19),"-") -> -
A20: 10. MERMAS, VENCIMIENTOS Y DESPERDICIO | B20: =COUNTIF('Checklist Inventario'!B105:B110,"X") -> 0 | C20: =COUNTIF('Checklist Inventario'!C105:C110,"X") -> 0 | D20: =IFERROR(B20/(B20+C20),"-") -> -
A21: 11. HIGIENE Y CONTROL DE PLAGAS DEL DEPÓSITO | B21: =COUNTIF('Checklist Inventario'!B114:B118,"X") -> 0 | C21: =COUNTIF('Checklist Inventario'!C114:C118,"X") -> 0 | D21: =IFERROR(B21/(B21+C21),"-") -> -
A22: 12. SEGURIDAD Y CONTROL DE ACCESO | B22: =COUNTIF('Checklist Inventario'!B122:B125,"X") -> 0 | C22: =COUNTIF('Checklist Inventario'!C122:C125,"X") -> 0 | D22: =IFERROR(B22/(B22+C22),"-") -> -
A23: 13. CONTROL DE BAR Y BEBIDAS | B23: =COUNTIF('Checklist Inventario'!B129:B142,"X") -> 0 | C23: =COUNTIF('Checklist Inventario'!C129:C142,"X") -> 0 | D23: =IFERROR(B23/(B23+C23),"-") -> -
A24: 14. UTENSILIOS, EQUIPOS Y VAJILLA | B24: =COUNTIF('Checklist Inventario'!B146:B158,"X") -> 0 | C24: =COUNTIF('Checklist Inventario'!C146:C158,"X") -> 0 | D24: =IFERROR(B24/(B24+C24),"-") -> -
A25: 15. COSTOS Y VALORIZACIÓN DEL INVENTARIO | B25: =COUNTIF('Checklist Inventario'!B162:B167,"X") -> 0 | C25: =COUNTIF('Checklist Inventario'!C162:C167,"X") -> 0 | D25: =IFERROR(B25/(B25+C25),"-") -> -
